ntsulib/__init__.py
ntsulib/__init__.pyi
ntsulib/py.typed
ntsulib/c/__init__.py
ntsulib/c/__init__.pyi
ntsulib/c/c_libs.pyd
ntsulib/c/c_libs.pyi
ntsulib/c/libs/ntsulib.dll
ntsulib/m_asyncthread/__init__.py
ntsulib/m_asyncthread/__init__.pyi
ntsulib/m_asyncthread/n_asyncthread.pyd
ntsulib/m_asyncthread/n_asyncthread.pyi
ntsulib/m_database/__init__.py
ntsulib/m_database/__init__.pyi
ntsulib/m_database/n_dbstatus.pyd
ntsulib/m_database/n_dbstatus.pyi
ntsulib/m_database/n_postgre.pyd
ntsulib/m_database/n_postgre.pyi
ntsulib/m_encry/__init__.py
ntsulib/m_encry/__init__.pyi
ntsulib/m_encry/n_encry.pyd
ntsulib/m_encry/n_encry.pyi
ntsulib/m_general/__init__.py
ntsulib/m_general/__init__.pyi
ntsulib/m_general/n_container.pyd
ntsulib/m_general/n_container.pyi
ntsulib/m_general/n_io.py
ntsulib/m_general/n_io.pyi
ntsulib/m_general/n_out.py
ntsulib/m_general/n_out.pyi
ntsulib/m_general/n_str.pyd
ntsulib/m_general/n_str.pyi
ntsulib/m_logger/__init__.py
ntsulib/m_logger/__init__.pyi
ntsulib/m_pyqt5/__init__.py
ntsulib/m_pyqt5/__init__.pyi
ntsulib/m_pyqt5/n_pyqt5.pyd
ntsulib/m_pyqt5/n_pyqt5.pyi
ntsulib/m_regular/__init__.py
ntsulib/m_regular/__init__.pyi
ntsulib/m_regular/n_regular.pyd
ntsulib/m_regular/n_regular.pyi
ntsulib/m_serverquery/__init__.py
ntsulib/m_serverquery/__init__.pyi
ntsulib/m_serverquery/n_gamequery.py
ntsulib/m_serverquery/n_gamequery.pyi
ntsulib/m_sys/__init__.py
ntsulib/m_sys/__init__.pyi
ntsulib/m_sys/n_sys.pyd
ntsulib/m_sys/n_sys.pyi
ntsulib/m_thread/__init__.py
ntsulib/m_thread/__init__.pyi
ntsulib/m_thread/n_thread.pyd
ntsulib/m_thread/n_thread.pyi
ntsulib-1.2.231.data/data/Lib/site-packages/PyInstaller/hooks/hook-ntsulib.py
ntsulib-1.2.231.dist-info/LICENSE
ntsulib-1.2.231.dist-info/METADATA
ntsulib-1.2.231.dist-info/WHEEL
ntsulib-1.2.231.dist-info/top_level.txt
ntsulib-1.2.231.dist-info/RECORD
