Metadata-Version: 2.1
Name: ntsulib
Version: 1.2.231
Summary: ntsulib
Home-page: 
Author: NTsukine
Author-email: NTsukine <398339897@qq.com>
Keywords: utility,library,python,ntsulib
Classifier: Development Status :: 4 - Beta
Classifier: License :: OSI Approved :: GNU General Public License v3 (GPLv3)
Classifier: Programming Language :: Python :: 3
Classifier: Programming Language :: Python :: 3.11
Requires-Python: >=3.11
License-File: LICENSE
Requires-Dist: certifi ==2025.1.31
Requires-Dist: chardet ==5.2.0
Requires-Dist: charset-normalizer ==3.4.1
Requires-Dist: idna ==3.10
Requires-Dist: psycopg2 ==2.9.10
Requires-Dist: PyQt5 ==5.15.11
Requires-Dist: PyQt5-Qt5 ==5.15.2
Requires-Dist: PyQt5-sip ==12.17.0
Requires-Dist: python-a2s ==1.4.1
Requires-Dist: requests ==2.32.3
Requires-Dist: urllib3 ==2.4.0
